better_sqlite/__init__.py
better_sqlite/main.py
better_sqlite-0.1.0.dist-info/LICENSE
better_sqlite-0.1.0.dist-info/METADATA
better_sqlite-0.1.0.dist-info/WHEEL
better_sqlite-0.1.0.dist-info/RECORD
