Metadata-Version: 2.1
Name: better-sqlite
Version: 0.1.0
Summary: A simple and intuitive SQLite wrapper library that provides an easy-to-use interface for interacting with SQLite databases, enabling basic CRUD operations without writing raw SQL.
Author: ayrun
Author-email: ayrun3412@gmail.com
Requires-Python: >=3.12,<4.0
Classifier: Programming Language :: Python :: 3
Classifier: Programming Language :: Python :: 3.12
